aliyunsdkpai_dsw/__init__.py
aliyunsdkpai_dsw/request/__init__.py
aliyunsdkpai_dsw/request/v20220101/CreateIdleInstanceCullerRequest.py
aliyunsdkpai_dsw/request/v20220101/CreateInstanceRequest.py
aliyunsdkpai_dsw/request/v20220101/CreateInstanceShutdownTimerRequest.py
aliyunsdkpai_dsw/request/v20220101/CreateInstanceSnapshotRequest.py
aliyunsdkpai_dsw/request/v20220101/DeleteIdleInstanceCullerRequest.py
aliyunsdkpai_dsw/request/v20220101/DeleteInstanceRequest.py
aliyunsdkpai_dsw/request/v20220101/DeleteInstanceShutdownTimerRequest.py
aliyunsdkpai_dsw/request/v20220101/DeleteInstanceSnapshotRequest.py
aliyunsdkpai_dsw/request/v20220101/GetIdleInstanceCullerRequest.py
aliyunsdkpai_dsw/request/v20220101/GetInstanceMetricsRequest.py
aliyunsdkpai_dsw/request/v20220101/GetInstanceRequest.py
aliyunsdkpai_dsw/request/v20220101/GetInstanceShutdownTimerRequest.py
aliyunsdkpai_dsw/request/v20220101/GetInstanceSnapshotRequest.py
aliyunsdkpai_dsw/request/v20220101/GetLifecycleRequest.py
aliyunsdkpai_dsw/request/v20220101/GetTokenRequest.py
aliyunsdkpai_dsw/request/v20220101/GetUserConfigRequest.py
aliyunsdkpai_dsw/request/v20220101/ListDemoCategoriesRequest.py
aliyunsdkpai_dsw/request/v20220101/ListDemosRequest.py
aliyunsdkpai_dsw/request/v20220101/ListEcsSpecsRequest.py
aliyunsdkpai_dsw/request/v20220101/ListInstanceSnapshotRequest.py
aliyunsdkpai_dsw/request/v20220101/ListInstanceStatisticsRequest.py
aliyunsdkpai_dsw/request/v20220101/ListInstancesRequest.py
aliyunsdkpai_dsw/request/v20220101/StartInstanceRequest.py
aliyunsdkpai_dsw/request/v20220101/StopInstanceRequest.py
aliyunsdkpai_dsw/request/v20220101/UpdateInstanceRequest.py
aliyunsdkpai_dsw/request/v20220101/__init__.py
aliyun_python_sdk_pai_dsw-1.0.0.dist-info/LICENSE
aliyun_python_sdk_pai_dsw-1.0.0.dist-info/METADATA
aliyun_python_sdk_pai_dsw-1.0.0.dist-info/WHEEL
aliyun_python_sdk_pai_dsw-1.0.0.dist-info/top_level.txt
aliyun_python_sdk_pai_dsw-1.0.0.dist-info/RECORD
